merge/__init__.py
merge/client.py
merge/core/__init__.py
merge/core/api_error.py
merge/core/client_wrapper.py
merge/core/datetime_utils.py
merge/core/file.py
merge/core/http_client.py
merge/core/jsonable_encoder.py
merge/core/pydantic_utilities.py
merge/core/query_encoder.py
merge/core/remove_none_from_dict.py
merge/core/request_options.py
merge/environment.py
merge/py.typed
merge/resources/__init__.py
merge/resources/accounting/__init__.py
merge/resources/accounting/client.py
merge/resources/accounting/resources/__init__.py
merge/resources/accounting/resources/account_details/__init__.py
merge/resources/accounting/resources/account_details/client.py
merge/resources/accounting/resources/account_token/__init__.py
merge/resources/accounting/resources/account_token/client.py
merge/resources/accounting/resources/accounting_periods/__init__.py
merge/resources/accounting/resources/accounting_periods/client.py
merge/resources/accounting/resources/accounts/__init__.py
merge/resources/accounting/resources/accounts/client.py
merge/resources/accounting/resources/accounts/types/__init__.py
merge/resources/accounting/resources/accounts/types/accounts_list_request_remote_fields.py
merge/resources/accounting/resources/accounts/types/accounts_list_request_show_enum_origins.py
merge/resources/accounting/resources/accounts/types/accounts_retrieve_request_remote_fields.py
merge/resources/accounting/resources/accounts/types/accounts_retrieve_request_show_enum_origins.py
merge/resources/accounting/resources/addresses/__init__.py
merge/resources/accounting/resources/addresses/client.py
merge/resources/accounting/resources/async_passthrough/__init__.py
merge/resources/accounting/resources/async_passthrough/client.py
merge/resources/accounting/resources/attachments/__init__.py
merge/resources/accounting/resources/attachments/client.py
merge/resources/accounting/resources/audit_trail/__init__.py
merge/resources/accounting/resources/audit_trail/client.py
mergepythonclient-1.0.13.dist-info/LICENSE.md
mergepythonclient-1.0.13.dist-info/METADATA
mergepythonclient-1.0.13.dist-info/WHEEL
mergepythonclient-1.0.13.dist-info/RECORD
